setup.py
tty.py
micropython_tty.egg-info/PKG-INFO
micropython_tty.egg-info/SOURCES.txt
micropython_tty.egg-info/dependency_links.txt
micropython_tty.egg-info/top_level.txt